jsmfsb/__init__.py
jsmfsb/data.py
jsmfsb/inference.py
jsmfsb/models.py
jsmfsb/sim.py
jsmfsb/smfsb_sbml.py
jsmfsb/spatial.py
jsmfsb/spn.py
jsmfsb-1.1.5.dist-info/METADATA
jsmfsb-1.1.5.dist-info/WHEEL
jsmfsb-1.1.5.dist-info/licenses/LICENSE
jsmfsb-1.1.5.dist-info/RECORD
